promisedio_buildtools/__init__.py
promisedio_buildtools/capsule.py
promisedio_buildtools/clinic.py
promisedio_buildtools/cpp.py
promisedio_buildtools/download_sources.py
promisedio_buildtools/extension.py
promisedio_buildtools/include/_promisedio/atomic.h
promisedio_buildtools/include/_promisedio/base.h
promisedio_buildtools/include/_promisedio/capsule.h
promisedio_buildtools/include/_promisedio/chain.h
promisedio_buildtools/include/_promisedio/memory.h
promisedio_buildtools/include/_promisedio/module.h
promisedio_buildtools/include/_promisedio/uv.h
promisedio_buildtools/include/clinic_converters/file.h
promisedio_buildtools/include/clinic_converters/inet.h
promisedio_buildtools/include/clinic_converters/numeric.h
promisedio_buildtools/include/clinic_converters/string.h
promisedio_buildtools/include/clinic_converters.h
promisedio_buildtools/include/promisedio.h
promisedio_buildtools/include/promisedio_uv.h
promisedio_buildtools/memcheck.py
promisedio_buildtools/pyclinic.py
promisedio_buildtools-1.0.30.dist-info/entry_points.txt
promisedio_buildtools-1.0.30.dist-info/LICENSE
promisedio_buildtools-1.0.30.dist-info/WHEEL
promisedio_buildtools-1.0.30.dist-info/METADATA
promisedio_buildtools-1.0.30.dist-info/RECORD
